{
    "archives": [
        {
            "month": "August",
            "beginMonth": 8,
            "beginDate": 1,
            "beginYear": 2021,
            "endMonth": 12,
            "endDate": 31,
            "endYear": 2024
        },
        {
            "month": "September",
            "beginMonth": 9,
            "beginDate": 1,
            "beginYear": 2021,
            "endMonth": 12,
            "endDate": 31,
            "endYear": 2024
        },
        {
            "month": "October",
            "beginMonth": 10,
            "beginDate": 1,
            "beginYear": 2021,
            "endMonth": 12,
            "endDate": 31,
            "endYear": 2024
        },
        {
            "month": "November",
            "beginMonth": 11,
            "beginDate": 1,
            "beginYear": 2021,
            "endMonth": 12,
            "endDate": 31,
            "endYear": 2024
        },
        {
            "month": "December",
            "beginMonth": 12,
            "beginDate": 1,
            "beginYear": 2021,
            "endMonth": 12,
            "endDate": 31,
            "endYear": 2024
        },
        {
            "month": "January",
            "beginMonth": 1,
            "beginDate": 1,
            "beginYear": 2022,
            "endMonth": 12,
            "endDate": 31,
            "endYear": 2025
        },
        {
            "month": "February",
            "beginMonth": 2,
            "beginDate": 1,
            "beginYear": 2022,
            "endMonth": 12,
            "endDate": 31,
            "endYear": 2025
        },
        {
            "month": "March",
            "beginMonth": 3,
            "beginDate": 1,
            "beginYear": 2022,
            "endMonth": 12,
            "endDate": 31,
            "endYear": 2025
        },
        {
            "month": "April",
            "beginMonth": 4,
            "beginDate": 1,
            "beginYear": 2022,
            "endMonth": 12,
            "endDate": 31,
            "endYear": 2025
        },
        {
            "month": "May",
            "beginMonth": 5,
            "beginDate": 1,
            "beginYear": 2022,
            "endMonth": 12,
            "endDate": 31,
            "endYear": 2025
        },
        {
            "month": "June",
            "beginMonth": 6,
            "beginDate": 1,
            "beginYear": 2022,
            "endMonth": 12,
            "endDate": 31,
            "endYear": 2025
        },
        {
            "month": "July",
            "beginMonth": 7,
            "beginDate": 1,
            "beginYear": 2022,
            "endMonth": 12,
            "endDate": 31,
            "endYear": 2025
        },
        {
            "month": "August",
            "beginMonth": 8,
            "beginDate": 1,
            "beginYear": 2022,
            "endMonth": 12,
            "endDate": 31,
            "endYear": 2025
        },
        {
            "month": "September",
            "beginMonth": 9,
            "beginDate": 1,
            "beginYear": 2022,
            "endMonth": 12,
            "endDate": 31,
            "endYear": 2025
        },
        {
            "month": "October",
            "beginMonth": 10,
            "beginDate": 1,
            "beginYear": 2022,
            "endMonth": 12,
            "endDate": 31,
            "endYear": 2025
        },
        {
            "month": "November",
            "beginMonth": 11,
            "beginDate": 1,
            "beginYear": 2022,
            "endMonth": 12,
            "endDate": 31,
            "endYear": 2025
        },
        {
            "month": "December",
            "beginMonth": 12,
            "beginDate": 1,
            "beginYear": 2022,
            "endMonth": 12,
            "endDate": 31,
            "endYear": 2025
        },
        {
            "month": "January",
            "beginMonth": 1,
            "beginDate": 1,
            "beginYear": 2023,
            "endMonth": 12,
            "endDate": 31,
            "endYear": 2026
        },
        {
            "month": "February",
            "beginMonth": 2,
            "beginDate": 1,
            "beginYear": 2023,
            "endMonth": 12,
            "endDate": 31,
            "endYear": 2026
        },
        {
            "month": "March",
            "beginMonth": 3,
            "beginDate": 1,
            "beginYear": 2023,
            "endMonth": 12,
            "endDate": 31,
            "endYear": 2026
        },
        {
            "month": "April",
            "beginMonth": 4,
            "beginDate": 1,
            "beginYear": 2023,
            "endMonth": 12,
            "endDate": 31,
            "endYear": 2026
        },
        {
            "month": "May",
            "beginMonth": 5,
            "beginDate": 1,
            "beginYear": 2023,
            "endMonth": 12,
            "endDate": 31,
            "endYear": 2026
        },
        {
            "month": "June",
            "beginMonth": 6,
            "beginDate": 1,
            "beginYear": 2023,
            "endMonth": 12,
            "endDate": 31,
            "endYear": 2026
        },
        {
            "month": "July",
            "beginMonth": 7,
            "beginDate": 1,
            "beginYear": 2023,
            "endMonth": 12,
            "endDate": 31,
            "endYear": 2026
        },
        {
            "month": "August",
            "beginMonth": 8,
            "beginDate": 1,
            "beginYear": 2023,
            "endMonth": 12,
            "endDate": 31,
            "endYear": 2026
        },
        {
            "month": "September",
            "beginMonth": 9,
            "beginDate": 1,
            "beginYear": 2023,
            "endMonth": 12,
            "endDate": 31,
            "endYear": 2026
        },
        {
            "month": "October",
            "beginMonth": 10,
            "beginDate": 1,
            "beginYear": 2023,
            "endMonth": 12,
            "endDate": 31,
            "endYear": 2026
        },
        {
            "month": "November",
            "beginMonth": 11,
            "beginDate": 1,
            "beginYear": 2023,
            "endMonth": 12,
            "endDate": 31,
            "endYear": 2026
        },
        {
            "month": "December",
            "beginMonth": 12,
            "beginDate": 1,
            "beginYear": 2023,
            "endMonth": 12,
            "endDate": 31,
            "endYear": 2026
        },
        {
            "month": "January",
            "beginMonth": 1,
            "beginDate": 1,
            "beginYear": 2024,
            "endMonth": 12,
            "endDate": 31,
            "endYear": 2027
        }
    ]
}